libloader/__init__.py
libloader/com.py
libloader/libloader.py
libloader-1.4.2.dist-info/METADATA
libloader-1.4.2.dist-info/WHEEL
libloader-1.4.2.dist-info/licenses/LICENSE
libloader-1.4.2.dist-info/RECORD
