Metadata-Version: 2.4
Name: libloader
Version: 1.4.2
Summary: Quickly and easily load shared libraries on various platforms. Also includes a libloader.com module for loading com modules on Windows.
Author-email: Christopher Toth <q@q-continuum.net>
License: Copyright (c) 2019 Christopher Toth
License-File: LICENSE
Classifier: Development Status :: 3 - Alpha
Classifier: Intended Audience :: Developers
Classifier: License :: OSI Approved :: MIT License
Classifier: Operating System :: OS Independent
Classifier: Programming Language :: Python :: 3
Classifier: Programming Language :: Python :: 3.8
Classifier: Programming Language :: Python :: 3.9
Classifier: Programming Language :: Python :: 3.10
Classifier: Programming Language :: Python :: 3.11
Classifier: Programming Language :: Python :: 3.12
Classifier: Programming Language :: Python :: 3.13
Classifier: Topic :: Software Development :: Libraries
Requires-Python: >=3.8
Requires-Dist: pywin32; sys_platform == 'win32'
